[
{"tema": "Administrativo", "subtema": "Administração pública: órgãos públicos"},
{"tema": "Administrativo", "subtema": "Licitação e contratos"},
{"tema": "Administrativo", "subtema": "Militares dos estados, DF e territórios"},
{"tema": "Administrativo", "subtema": "Organização político-administrativa do Estado"},
{"tema": "Administrativo", "subtema": "Servidores públicos"},
{"tema": "Econômico", "subtema": "Agricultura, pecuária, pesca e abastecimento"},
{"tema": "Econômico", "subtema": "Desenvolvimento regional"},
{"tema": "Econômico", "subtema": "Fiscalização e controle"},
{"tema": "Econômico", "subtema": "Indústria, comércio e abastecimento"},
{"tema": "Econômico", "subtema": "Minas e energia"},
{"tema": "Econômico", "subtema": "Planejamento e orçamento"},
{"tema": "Econômico", "subtema": "Política econômica e sistema financeiro"},
{"tema": "Econômico", "subtema": "Política fundiária e reforma agrária"},
{"tema": "Econômico", "subtema": "Política urbana"},
{"tema": "Econômico", "subtema": "Recursos hídricos"},
{"tema": "Econômico", "subtema": "Tributação"},
{"tema": "Econômico", "subtema": "Turismo"},
{"tema": "Econômico", "subtema": "Utilidade Pública"},
{"tema": "Econômico", "subtema": "Viação, transportes e trânsito"},
{"tema": "Econômico", "subtema": "Zona de processamento de exportação"},
{"tema": "Honorífico", "subtema": "Homenagens e Data Comemorativas"},
{"tema": "Jurídico", "subtema": "Defesa do consumidor"},
{"tema": "Jurídico", "subtema": "Defesa nacional e forças armadas"},
{"tema": "Jurídico", "subtema": "Direito aeronáutico e direito espacial"},
{"tema": "Jurídico", "subtema": "Direito civil e processual civil"},
{"tema": "Jurídico", "subtema": "Direito comercial e econômico"},
{"tema": "Jurídico", "subtema": "Direito Constitucional"},
{"tema": "Jurídico", "subtema": "Direito do trabalho e processual do Trabalho"},
{"tema": "Jurídico", "subtema": "Direito dos estrangeiros"},
{"tema": "Jurídico", "subtema": "Direito e Justiça"},
{"tema": "Jurídico", "subtema": "Direito eleitoral e partidos políticos"},
{"tema": "Jurídico", "subtema": "Direito marítimo"},
{"tema": "Jurídico", "subtema": "Direito penal e processual penal"},
{"tema": "Jurídico", "subtema": "Direitos políticos, nacionalidade e cidadania"},
{"tema": "Jurídico", "subtema": "Processo legislativo"},
{"tema": "Jurídico", "subtema": "Relações internacionais"},
{"tema": "Jurídico", "subtema": "Segurança pública"},
{"tema": "Outros", "subtema": "Diversos"},
{"tema": "Social", "subtema": "Arte e cultura"},
{"tema": "Social", "subtema": "Assistência social"},
{"tema": "Social", "subtema": "Ciência, tecnologia e informática"},
{"tema": "Social", "subtema": "Comunicações"},
{"tema": "Social", "subtema": "Desenvolvimento social e combate à fome"},
{"tema": "Social", "subtema": "Desporto e lazer"},
{"tema": "Social", "subtema": "Direitos humanos e minorias"},
{"tema": "Social", "subtema": "Drogas"},
{"tema": "Social", "subtema": "Educação"},
{"tema": "Social", "subtema": "Família, proteção a crianças, adolescentes, mulheres e idosos"},
{"tema": "Social", "subtema": "Meio ambiente"},
{"tema": "Social", "subtema": "Previdência social"},
{"tema": "Social", "subtema": "Saúde"},
{"tema": "Social", "subtema": "Trabalho, emprego e renda"}
]
